opentelemetry/exporter/prometheus/__init__.py
opentelemetry/exporter/prometheus/version.py
opentelemetry_exporter_prometheus-1.12.0rc1.dist-info/LICENSE
opentelemetry_exporter_prometheus-1.12.0rc1.dist-info/METADATA
opentelemetry_exporter_prometheus-1.12.0rc1.dist-info/WHEEL
opentelemetry_exporter_prometheus-1.12.0rc1.dist-info/entry_points.txt
opentelemetry_exporter_prometheus-1.12.0rc1.dist-info/top_level.txt
opentelemetry_exporter_prometheus-1.12.0rc1.dist-info/RECORD
