Metadata-Version: 2.1
Name: opentelemetry-exporter-prometheus
Version: 1.12.0rc1
Summary: Prometheus Metric Exporter for OpenTelemetry
Home-page: https://github.com/open-telemetry/opentelemetry-python/tree/main/exporter/opentelemetry-exporter-prometheus
Author: OpenTelemetry Authors
Author-email: cncf-opentelemetry-contributors@lists.cncf.io
License: Apache-2.0
Platform: any
Classifier: Development Status :: 4 - Beta
Classifier: Intended Audience :: Developers
Classifier: License :: OSI Approved :: Apache Software License
Classifier: Programming Language :: Python
Classifier: Programming Language :: Python :: 3
Classifier: Programming Language :: Python :: 3.6
Classifier: Programming Language :: Python :: 3.7
Classifier: Programming Language :: Python :: 3.8
Classifier: Programming Language :: Python :: 3.9
Classifier: Programming Language :: Python :: 3.10
Requires-Python: >=3.6
Provides-Extra: test
License-File: LICENSE
